{
  "date": "2026-07-16",
  "updated": "2026-07-16 15:03:05.978948",
  "method": "BlackRock 4/3/2/1",
  "data_freshness": {
    "财报": "✅ 财报: 0天前 (>120天警告)",
    "股东户数": "✅ 股东户数: 0天前 (>90天警告)",
    "公告": "✅ 公告: 0天前 (>60天警告)",
    "分析师": "✅ 分析师: 0天前 (>30天警告)"
  },
  "top30": [
    {
      "rank": 1,
      "symbol": "002582",
      "name": "好想你",
      "industry": "食品饮料",
      "score": 3.054,
      "factors": {
        "value_ep": 0.4545,
        "value_bp": 1.1364,
        "size": 0.0,
        "momentum_price": -0.0724,
        "momentum_risk_adj": -0.1789,
        "momentum_earn": NaN,
        "reversal": -0.016,
        "quality_roe": 24.46,
        "quality_leverage": -0.5,
        "quality_fscore": 0.33,
        "alt_visits": 4,
        "strategic_tier": 3
      }
    },
    {
      "rank": 2,
      "symbol": "688585",
      "name": "上纬新材",
      "industry": "行业-1",
      "score": 2.309,
      "factors": {
        "value_ep": NaN,
        "value_bp": 0.0236,
        "size": -24.7311,
        "momentum_price": 22.6184,
        "momentum_risk_adj": 19.6324,
        "momentum_earn": NaN,
        "reversal": 0.1692,
        "quality_roe": -3.12,
        "quality_leverage": -41.7856,
        "quality_fscore": 0.0,
        "alt_visits": 1,
        "strategic_tier": 0
      }
    },
    {
      "rank": 3,
      "symbol": "301377",
      "name": "鼎泰高科",
      "industry": "行业-1",
      "score": 1.91,
      "factors": {
        "value_ep": 0.0032,
        "value_bp": 0.0138,
        "size": -24.5474,
        "momentum_price": 15.7328,
        "momentum_risk_adj": 18.3085,
        "momentum_earn": NaN,
        "reversal": 0.1633,
        "quality_roe": 9.38,
        "quality_leverage": -45.5358,
        "quality_fscore": 0.17,
        "alt_visits": 5,
        "strategic_tier": 0
      }
    },
    {
      "rank": 4,
      "symbol": "600841",
      "name": "动力新科",
      "industry": "行业-1",
      "score": 1.896,
      "factors": {
        "value_ep": 0.3802,
        "value_bp": 0.7812,
        "size": -22.5403,
        "momentum_price": 0.0643,
        "momentum_risk_adj": 0.1224,
        "momentum_earn": NaN,
        "reversal": 0.1311,
        "quality_roe": 0.57,
        "quality_leverage": -0.5,
        "quality_fscore": 0.33,
        "alt_visits": 0,
        "strategic_tier": 0
      }
    },
    {
      "rank": 5,
      "symbol": "001309",
      "name": "德明利",
      "industry": "半导体",
      "score": 1.894,
      "factors": {
        "value_ep": 0.0303,
        "value_bp": 0.049,
        "size": -25.3124,
        "momentum_price": 4.9985,
        "momentum_risk_adj": 6.0303,
        "momentum_earn": NaN,
        "reversal": 0.0907,
        "quality_roe": 67.45,
        "quality_leverage": -63.9726,
        "quality_fscore": 0.17,
        "alt_visits": 8,
        "strategic_tier": 1
      }
    },
    {
      "rank": 6,
      "symbol": "000430",
      "name": "张家界",
      "industry": "旅游酒店",
      "score": 1.732,
      "factors": {
        "value_ep": NaN,
        "value_bp": 0.3584,
        "size": 0.0,
        "momentum_price": -0.0401,
        "momentum_risk_adj": -0.1139,
        "momentum_earn": NaN,
        "reversal": 0.1931,
        "quality_roe": 69.14,
        "quality_leverage": -29.8708,
        "quality_fscore": 0.17,
        "alt_visits": 0,
        "strategic_tier": 3
      }
    },
    {
      "rank": 7,
      "symbol": "603256",
      "name": "宏和科技",
      "industry": "行业-1",
      "score": 1.682,
      "factors": {
        "value_ep": 0.0019,
        "value_bp": 0.0169,
        "size": -25.7713,
        "momentum_price": 13.6935,
        "momentum_risk_adj": 16.212,
        "momentum_earn": NaN,
        "reversal": 0.2964,
        "quality_roe": 8.15,
        "quality_leverage": -38.4384,
        "quality_fscore": 0.17,
        "alt_visits": 0,
        "strategic_tier": 0
      }
    },
    {
      "rank": 8,
      "symbol": "002958",
      "name": "青农商行",
      "industry": "银行",
      "score": 1.503,
      "factors": {
        "value_ep": 0.1934,
        "value_bp": 2.2727,
        "size": -23.5055,
        "momentum_price": -0.227,
        "momentum_risk_adj": -1.2253,
        "momentum_earn": NaN,
        "reversal": -0.0312,
        "quality_roe": 3.05,
        "quality_leverage": -0.5,
        "quality_fscore": 0.33,
        "alt_visits": 9,
        "strategic_tier": 3
      }
    },
    {
      "rank": 9,
      "symbol": "601997",
      "name": "贵阳银行",
      "industry": "行业-1",
      "score": 1.454,
      "factors": {
        "value_ep": 0.266,
        "value_bp": 3.2258,
        "size": -23.7116,
        "momentum_price": -0.1308,
        "momentum_risk_adj": -0.701,
        "momentum_earn": NaN,
        "reversal": 0.0423,
        "quality_roe": 2.27,
        "quality_leverage": -90.4476,
        "quality_fscore": 0.17,
        "alt_visits": 6,
        "strategic_tier": 0
      }
    },
    {
      "rank": 10,
      "symbol": "002839",
      "name": "张家港行",
      "industry": "银行",
      "score": 1.398,
      "factors": {
        "value_ep": 0.1887,
        "value_bp": 1.7857,
        "size": -23.0793,
        "momentum_price": -0.0925,
        "momentum_risk_adj": -0.4741,
        "momentum_earn": NaN,
        "reversal": -0.0213,
        "quality_roe": 3.06,
        "quality_leverage": -0.5,
        "quality_fscore": 0.33,
        "alt_visits": 13,
        "strategic_tier": 3
      }
    },
    {
      "rank": 11,
      "symbol": "002807",
      "name": "江阴银行",
      "industry": "银行",
      "score": 1.375,
      "factors": {
        "value_ep": 0.1908,
        "value_bp": 1.8182,
        "size": -23.0991,
        "momentum_price": -0.1972,
        "momentum_risk_adj": -0.818,
        "momentum_earn": NaN,
        "reversal": 0.0,
        "quality_roe": 1.85,
        "quality_leverage": -0.5,
        "quality_fscore": 0.33,
        "alt_visits": 7,
        "strategic_tier": 3
      }
    },
    {
      "rank": 12,
      "symbol": "000498",
      "name": "山东路桥",
      "industry": "工程建设",
      "score": 1.341,
      "factors": {
        "value_ep": 0.2732,
        "value_bp": 2.0833,
        "size": -22.7157,
        "momentum_price": -0.1419,
        "momentum_risk_adj": -0.7167,
        "momentum_earn": NaN,
        "reversal": -0.002,
        "quality_roe": 0.32,
        "quality_leverage": -76.0158,
        "quality_fscore": 0.17,
        "alt_visits": 5,
        "strategic_tier": 3
      }
    },
    {
      "rank": 13,
      "symbol": "002842",
      "name": "翔鹭钨业",
      "industry": "小金属",
      "score": 1.317,
      "factors": {
        "value_ep": 0.0343,
        "value_bp": 0.1256,
        "size": -22.9471,
        "momentum_price": 4.1459,
        "momentum_risk_adj": 5.8184,
        "momentum_earn": NaN,
        "reversal": 0.2572,
        "quality_roe": 18.79,
        "quality_leverage": -0.5,
        "quality_fscore": 0.33,
        "alt_visits": 2,
        "strategic_tier": 3
      }
    },
    {
      "rank": 14,
      "symbol": "301217",
      "name": "铜冠铜箔",
      "industry": "行业-1",
      "score": 1.314,
      "factors": {
        "value_ep": 0.0016,
        "value_bp": 0.0522,
        "size": -25.3816,
        "momentum_price": 12.1659,
        "momentum_risk_adj": 12.5005,
        "momentum_earn": NaN,
        "reversal": 0.286,
        "quality_roe": 1.95,
        "quality_leverage": -29.4993,
        "quality_fscore": 0.17,
        "alt_visits": 3,
        "strategic_tier": 0
      }
    },
    {
      "rank": 15,
      "symbol": "600908",
      "name": "无锡银行",
      "industry": "行业-1",
      "score": 1.299,
      "factors": {
        "value_ep": 0.1953,
        "value_bp": 1.9231,
        "size": -23.108,
        "momentum_price": -0.1626,
        "momentum_risk_adj": -0.8873,
        "momentum_earn": NaN,
        "reversal": 0.0145,
        "quality_roe": 2.79,
        "quality_leverage": -0.5,
        "quality_fscore": 0.33,
        "alt_visits": 3,
        "strategic_tier": 0
      }
    },
    {
      "rank": 16,
      "symbol": "301308",
      "name": "江波龙",
      "industry": "行业-1",
      "score": 1.295,
      "factors": {
        "value_ep": 0.0277,
        "value_bp": 0.0615,
        "size": -25.5959,
        "momentum_price": 5.6629,
        "momentum_risk_adj": 6.7469,
        "momentum_earn": NaN,
        "reversal": 0.1419,
        "quality_roe": 39.4,
        "quality_leverage": -65.5502,
        "quality_fscore": 0.17,
        "alt_visits": 36,
        "strategic_tier": 0
      }
    },
    {
      "rank": 17,
      "symbol": "002636",
      "name": "金安国纪",
      "industry": "电子元件",
      "score": 1.273,
      "factors": {
        "value_ep": 0.0074,
        "value_bp": 0.0571,
        "size": -24.8955,
        "momentum_price": 8.2832,
        "momentum_risk_adj": 10.7856,
        "momentum_earn": NaN,
        "reversal": 0.1176,
        "quality_roe": 5.44,
        "quality_leverage": -0.5,
        "quality_fscore": 0.33,
        "alt_visits": 3,
        "strategic_tier": 1
      }
    },
    {
      "rank": 18,
      "symbol": "600928",
      "name": "西安银行",
      "industry": "行业-1",
      "score": 1.252,
      "factors": {
        "value_ep": 0.1698,
        "value_bp": 2.2222,
        "size": -23.4827,
        "momentum_price": -0.1247,
        "momentum_risk_adj": -0.4935,
        "momentum_earn": NaN,
        "reversal": -0.0113,
        "quality_roe": 2.13,
        "quality_leverage": -0.5,
        "quality_fscore": 0.33,
        "alt_visits": 0,
        "strategic_tier": 0
      }
    },
    {
      "rank": 19,
      "symbol": "002948",
      "name": "青岛银行",
      "industry": "银行",
      "score": 1.251,
      "factors": {
        "value_ep": 0.1675,
        "value_bp": 1.2821,
        "size": -23.7033,
        "momentum_price": 0.1381,
        "momentum_risk_adj": 0.4897,
        "momentum_earn": NaN,
        "reversal": 0.0278,
        "quality_roe": 3.6575,
        "quality_leverage": -0.5,
        "quality_fscore": 0.33,
        "alt_visits": 13,
        "strategic_tier": 3
      }
    },
    {
      "rank": 20,
      "symbol": "600015",
      "name": "华夏银行",
      "industry": "行业-1",
      "score": 1.234,
      "factors": {
        "value_ep": 0.2463,
        "value_bp": 2.9412,
        "size": -25.3912,
        "momentum_price": -0.1663,
        "momentum_risk_adj": -0.9237,
        "momentum_earn": NaN,
        "reversal": -0.0087,
        "quality_roe": 1.57,
        "quality_leverage": -91.6869,
        "quality_fscore": 0.17,
        "alt_visits": 0,
        "strategic_tier": 0
      }
    },
    {
      "rank": 21,
      "symbol": "600016",
      "name": "民生银行",
      "industry": "行业-1",
      "score": 1.229,
      "factors": {
        "value_ep": 0.1942,
        "value_bp": 3.8462,
        "size": -25.5301,
        "momentum_price": -0.2808,
        "momentum_risk_adj": -1.4952,
        "momentum_earn": NaN,
        "reversal": 0.039,
        "quality_roe": 2.02,
        "quality_leverage": -90.9026,
        "quality_fscore": 0.17,
        "alt_visits": 0,
        "strategic_tier": 0
      }
    },
    {
      "rank": 22,
      "symbol": "688525",
      "name": "佰维存储",
      "industry": "行业-1",
      "score": 1.206,
      "factors": {
        "value_ep": 0.0279,
        "value_bp": 0.0605,
        "size": -25.6762,
        "momentum_price": 4.5807,
        "momentum_risk_adj": 5.5388,
        "momentum_earn": NaN,
        "reversal": 0.1182,
        "quality_roe": 41.98,
        "quality_leverage": -64.9551,
        "quality_fscore": 0.17,
        "alt_visits": 19,
        "strategic_tier": 0
      }
    },
    {
      "rank": 23,
      "symbol": "688766",
      "name": "普冉股份",
      "industry": "行业-1",
      "score": 1.185,
      "factors": {
        "value_ep": 0.0056,
        "value_bp": 0.0344,
        "size": -25.0828,
        "momentum_price": 8.355,
        "momentum_risk_adj": 8.9162,
        "momentum_earn": NaN,
        "reversal": -0.0879,
        "quality_roe": 9.88,
        "quality_leverage": -0.5,
        "quality_fscore": 0.33,
        "alt_visits": 7,
        "strategic_tier": 0
      }
    },
    {
      "rank": 24,
      "symbol": "300308",
      "name": "中际旭创",
      "industry": "行业-1",
      "score": 1.182,
      "factors": {
        "value_ep": 0.012,
        "value_bp": 0.0279,
        "size": -27.8424,
        "momentum_price": 7.9703,
        "momentum_risk_adj": 10.9733,
        "momentum_earn": NaN,
        "reversal": 0.1082,
        "quality_roe": 17.54,
        "quality_leverage": -32.6362,
        "quality_fscore": 0.17,
        "alt_visits": 8,
        "strategic_tier": 0
      }
    },
    {
      "rank": 25,
      "symbol": "002966",
      "name": "苏州银行",
      "industry": "银行",
      "score": 1.154,
      "factors": {
        "value_ep": 0.1553,
        "value_bp": 1.4493,
        "size": -24.2694,
        "momentum_price": -0.1426,
        "momentum_risk_adj": -0.7131,
        "momentum_earn": NaN,
        "reversal": 0.0211,
        "quality_roe": 3.08,
        "quality_leverage": -0.5,
        "quality_fscore": 0.33,
        "alt_visits": 18,
        "strategic_tier": 3
      }
    },
    {
      "rank": 26,
      "symbol": "601186",
      "name": "中国铁建",
      "industry": "行业-1",
      "score": 1.144,
      "factors": {
        "value_ep": 0.2037,
        "value_bp": 3.2258,
        "size": -25.0175,
        "momentum_price": -0.198,
        "momentum_risk_adj": -1.2489,
        "momentum_earn": NaN,
        "reversal": -0.0063,
        "quality_roe": 1.38,
        "quality_leverage": -79.5691,
        "quality_fscore": 0.17,
        "alt_visits": 1,
        "strategic_tier": 0
      }
    },
    {
      "rank": 27,
      "symbol": "601869",
      "name": "长飞光纤",
      "industry": "行业-1",
      "score": 1.114,
      "factors": {
        "value_ep": 0.0035,
        "value_bp": 0.0428,
        "size": -25.8185,
        "momentum_price": 10.6908,
        "momentum_risk_adj": 13.2274,
        "momentum_earn": NaN,
        "reversal": 0.1344,
        "quality_roe": 3.53,
        "quality_leverage": -49.2978,
        "quality_fscore": 0.17,
        "alt_visits": 3,
        "strategic_tier": 0
      }
    },
    {
      "rank": 28,
      "symbol": "600961",
      "name": "株冶集团",
      "industry": "行业-1",
      "score": 1.105,
      "factors": {
        "value_ep": 0.0784,
        "value_bp": 0.1988,
        "size": -23.6022,
        "momentum_price": 1.3504,
        "momentum_risk_adj": 2.1546,
        "momentum_earn": NaN,
        "reversal": 0.1285,
        "quality_roe": 25.3,
        "quality_leverage": -0.5,
        "quality_fscore": 0.33,
        "alt_visits": 0,
        "strategic_tier": 0
      }
    },
    {
      "rank": 29,
      "symbol": "300620",
      "name": "光库科技",
      "industry": "行业-1",
      "score": 1.097,
      "factors": {
        "value_ep": 0.0031,
        "value_bp": 0.0317,
        "size": -24.9348,
        "momentum_price": 8.0997,
        "momentum_risk_adj": 8.7939,
        "momentum_earn": NaN,
        "reversal": 0.3044,
        "quality_roe": 2.05,
        "quality_leverage": -0.5,
        "quality_fscore": 0.33,
        "alt_visits": 1,
        "strategic_tier": 0
      }
    },
    {
      "rank": 30,
      "symbol": "688308",
      "name": "欧科亿",
      "industry": "行业-1",
      "score": 1.092,
      "factors": {
        "value_ep": 0.0169,
        "value_bp": 0.1595,
        "size": -23.5999,
        "momentum_price": 8.4821,
        "momentum_risk_adj": 10.2274,
        "momentum_earn": NaN,
        "reversal": 0.3221,
        "quality_roe": 6.99,
        "quality_leverage": -38.0958,
        "quality_fscore": 0.17,
        "alt_visits": 54,
        "strategic_tier": 0
      }
    }
  ]
}